{
 "date": "2026-07-01",
 "sport": "MLB",
 "generated_at": "2026-07-01T23:05:13.743984Z",
 "record": {
  "w": 697,
  "l": 608,
  "pct": 0.534,
  "hi_w": 314,
  "hi_l": 264,
  "hi_pct": 0.543,
  "days": 100,
  "n": 1305,
  "span_start": "2026-03-21",
  "span_end": "2026-06-30",
  "graded_at": "2026-07-01T12:30:43.625473Z",
  "top_w": 85,
  "top_l": 58,
  "top_pct": 0.594,
  "top_threshold": 0.7
 },
 "calibration": {
  "ece": 0.0829,
  "mce": 0.3787,
  "brier": 0.2572,
  "n_picks": 1305,
  "overconfidence": 0.0673,
  "overall_realized": 0.5341,
  "graded_at": "2026-07-01T12:33:43.561039Z"
 },
 "games": [
  {
   "away": "Cincinnati Reds",
   "home": "Milwaukee Brewers",
   "pick": "Cincinnati Reds",
   "model": 0.526,
   "market": 0.367,
   "edge": 0.159,
   "model_side": "Cincinnati Reds",
   "model_conf": 0.526,
   "raw_conf": 0.536,
   "raw_model": 0.536,
   "calibrated": true,
   "dec_odds": 2.615,
   "best_dec_odds": 2.71,
   "start": "2026-07-02T18:11:00Z",
   "hp": "Shane Drohan",
   "ap": "Andrew Abbott",
   "hp_stat": {
    "era": "3.12",
    "w": 3,
    "l": 2,
    "ip": "52.0",
    "so": 52
   },
   "ap_stat": {
    "era": "3.90",
    "w": 5,
    "l": 4,
    "ip": "90.0",
    "so": 70
   }
  },
  {
   "away": "San Francisco Giants",
   "home": "Arizona Diamondbacks",
   "pick": "San Francisco Giants",
   "model": 0.531,
   "market": 0.453,
   "edge": 0.078,
   "model_side": "San Francisco Giants",
   "model_conf": 0.531,
   "raw_conf": 0.588,
   "raw_model": 0.588,
   "calibrated": true,
   "dec_odds": 2.12,
   "best_dec_odds": 2.16,
   "start": "2026-07-02T01:41:00Z",
   "hp": "Zac Gallen",
   "ap": "Trevor McDonald",
   "hp_stat": {
    "era": "6.15",
    "w": 3,
    "l": 7,
    "ip": "86.1",
    "so": 52
   },
   "ap_stat": {
    "era": "4.94",
    "w": 2,
    "l": 6,
    "ip": "51.0",
    "so": 45
   }
  },
  {
   "away": "Detroit Tigers",
   "home": "New York Yankees",
   "pick": "Detroit Tigers",
   "model": 0.533,
   "market": 0.456,
   "edge": 0.076,
   "model_side": "Detroit Tigers",
   "model_conf": 0.533,
   "raw_conf": 0.609,
   "raw_model": 0.609,
   "calibrated": true,
   "dec_odds": 2.1,
   "best_dec_odds": 2.23,
   "start": "2026-07-01T17:36:00Z",
   "hp": "Will Warren",
   "ap": "Troy Melton",
   "hp_stat": {
    "era": "3.75",
    "w": 7,
    "l": 3,
    "ip": "84.0",
    "so": 84
   },
   "ap_stat": {
    "era": "2.39",
    "w": 4,
    "l": 1,
    "ip": "37.2",
    "so": 25
   },
   "changed": "edge +9.6\u2192+7.6",
   "frozen": true
  },
  {
   "away": "Pittsburgh Pirates",
   "home": "Philadelphia Phillies",
   "pick": "Pittsburgh Pirates",
   "model": 0.534,
   "market": 0.458,
   "edge": 0.076,
   "model_side": "Pittsburgh Pirates",
   "model_conf": 0.534,
   "raw_conf": 0.625,
   "raw_model": 0.625,
   "calibrated": true,
   "dec_odds": 2.1,
   "best_dec_odds": 2.14,
   "start": "2026-07-02T16:36:00Z",
   "hp": "Zack Wheeler",
   "ap": "Paul Skenes",
   "hp_stat": {
    "era": "1.98",
    "w": 8,
    "l": 1,
    "ip": "77.1",
    "so": 77
   },
   "ap_stat": {
    "era": "3.06",
    "w": 6,
    "l": 7,
    "ip": "94.0",
    "so": 115
   }
  },
  {
   "away": "Los Angeles Dodgers",
   "home": "Athletics",
   "pick": "Athletics",
   "model": 0.464,
   "market": 0.399,
   "edge": 0.065,
   "model_side": "Los Angeles Dodgers",
   "model_conf": 0.536,
   "raw_conf": 0.65,
   "raw_model": 0.35,
   "calibrated": true,
   "dec_odds": 2.41,
   "best_dec_odds": 2.48,
   "start": "2026-07-02T01:41:00Z",
   "hp": "J.T. Ginn",
   "ap": "",
   "hp_stat": {
    "era": "3.15",
    "w": 6,
    "l": 4,
    "ip": "88.2",
    "so": 78
   },
   "ap_stat": null
  },
  {
   "away": "Tampa Bay Rays",
   "home": "Kansas City Royals",
   "pick": "Kansas City Royals",
   "model": 0.471,
   "market": 0.423,
   "edge": 0.048,
   "model_side": "Tampa Bay Rays",
   "model_conf": 0.529,
   "raw_conf": 0.571,
   "raw_model": 0.429,
   "calibrated": true,
   "dec_odds": 2.25,
   "best_dec_odds": 2.35,
   "start": "2026-07-01T23:41:00Z",
   "hp": "Seth Lugo",
   "ap": "Shane McClanahan",
   "hp_stat": {
    "era": "4.18",
    "w": 3,
    "l": 5,
    "ip": "90.1",
    "so": 69
   },
   "ap_stat": {
    "era": "3.30",
    "w": 6,
    "l": 5,
    "ip": "73.2",
    "so": 73
   }
  },
  {
   "away": "Chicago White Sox",
   "home": "Baltimore Orioles",
   "pick": "Baltimore Orioles",
   "model": 0.599,
   "market": 0.561,
   "edge": 0.039,
   "model_side": "Baltimore Orioles",
   "model_conf": 0.599,
   "raw_conf": 0.731,
   "raw_model": 0.731,
   "calibrated": true,
   "dec_odds": 1.714,
   "best_dec_odds": 1.752,
   "start": "2026-07-01T16:36:00Z",
   "hp": "Dean Kremer",
   "ap": "Noah Schultz",
   "hp_stat": {
    "era": "4.09",
    "w": 0,
    "l": 1,
    "ip": "11.0",
    "so": 16
   },
   "ap_stat": {
    "era": "5.82",
    "w": 2,
    "l": 4,
    "ip": "38.2",
    "so": 33
   },
   "changed": "edge +0.9\u2192+3.9 \u00b7 conf 57%\u219260% \u00b7 Bal SP TBD\u2192Dean Kremer",
   "frozen": true
  },
  {
   "away": "Texas Rangers",
   "home": "Cleveland Guardians",
   "pick": "Cleveland Guardians",
   "model": 0.568,
   "market": 0.532,
   "edge": 0.036,
   "model_side": "Cleveland Guardians",
   "model_conf": 0.568,
   "raw_conf": 0.702,
   "raw_model": 0.702,
   "calibrated": true,
   "dec_odds": 1.806,
   "best_dec_odds": 1.833,
   "start": "2026-07-01T17:11:00Z",
   "hp": "Joey Cantillo",
   "ap": "MacKenzie Gore",
   "hp_stat": {
    "era": "3.87",
    "w": 6,
    "l": 3,
    "ip": "86.0",
    "so": 85
   },
   "ap_stat": {
    "era": "4.05",
    "w": 5,
    "l": 6,
    "ip": "91.0",
    "so": 97
   },
   "frozen": true
  },
  {
   "away": "Minnesota Twins",
   "home": "Houston Astros",
   "pick": "Minnesota Twins",
   "model": 0.454,
   "market": 0.435,
   "edge": 0.019,
   "model_side": "Houston Astros",
   "model_conf": 0.546,
   "raw_conf": 0.68,
   "raw_model": 0.32,
   "calibrated": true,
   "dec_odds": 2.22,
   "best_dec_odds": 2.25,
   "start": "2026-07-02T00:11:00Z",
   "hp": "Tatsuya Imai",
   "ap": "Taj Bradley",
   "hp_stat": {
    "era": "5.36",
    "w": 5,
    "l": 3,
    "ip": "47.0",
    "so": 58
   },
   "ap_stat": {
    "era": "3.98",
    "w": 6,
    "l": 3,
    "ip": "83.2",
    "so": 91
   }
  },
  {
   "away": "Washington Nationals",
   "home": "Boston Red Sox",
   "pick": "Washington Nationals",
   "model": 0.445,
   "market": 0.427,
   "edge": 0.018,
   "model_side": "Boston Red Sox",
   "model_conf": 0.555,
   "raw_conf": 0.689,
   "raw_model": 0.311,
   "calibrated": true,
   "dec_odds": 2.26,
   "best_dec_odds": 2.29,
   "start": "2026-07-01T17:36:00Z",
   "hp": "Payton Tolle",
   "ap": "Brad Lord",
   "hp_stat": {
    "era": "2.78",
    "w": 4,
    "l": 5,
    "ip": "71.1",
    "so": 69
   },
   "ap_stat": {
    "era": "3.31",
    "w": 5,
    "l": 1,
    "ip": "54.1",
    "so": 51
   },
   "changed": "conf 59%\u219256% \u00b7 price -140\u2192+129 \u00b7 Was SP Andrew Alvarez\u2192Brad Lord \u00b7 pick\u2192Washington Nationals",
   "frozen": true
  },
  {
   "away": "St. Louis Cardinals",
   "home": "Atlanta Braves",
   "pick": "Atlanta Braves",
   "model": 0.525,
   "market": 0.509,
   "edge": 0.016,
   "model_side": "Atlanta Braves",
   "model_conf": 0.525,
   "raw_conf": 0.517,
   "raw_model": 0.517,
   "calibrated": true,
   "dec_odds": 1.893,
   "best_dec_odds": 1.893,
   "start": "2026-07-02T23:16:00Z",
   "hp": "Reynaldo L\u00f3pez",
   "ap": "Michael McGreevy",
   "hp_stat": {
    "era": "3.47",
    "w": 3,
    "l": 1,
    "ip": "46.2",
    "so": 40
   },
   "ap_stat": {
    "era": "3.12",
    "w": 3,
    "l": 6,
    "ip": "89.1",
    "so": 57
   },
   "changed": "edge +3.0\u2192+1.6 \u00b7 price +118\u2192-112 \u00b7 pick\u2192Atlanta Braves"
  },
  {
   "away": "New York Mets",
   "home": "Toronto Blue Jays",
   "pick": "Toronto Blue Jays",
   "model": 0.525,
   "market": 0.513,
   "edge": 0.012,
   "model_side": "Toronto Blue Jays",
   "model_conf": 0.525,
   "raw_conf": 0.53,
   "raw_model": 0.53,
   "calibrated": true,
   "dec_odds": 1.885,
   "best_dec_odds": 1.901,
   "start": "2026-07-01T19:08:00Z",
   "hp": "Braydon Fisher",
   "ap": "Freddy Peralta",
   "hp_stat": {
    "era": "3.48",
    "w": 3,
    "l": 3,
    "ip": "44.0",
    "so": 42
   },
   "ap_stat": {
    "era": "4.53",
    "w": 5,
    "l": 6,
    "ip": "91.1",
    "so": 88
   },
   "frozen": true
  },
  {
   "away": "San Diego Padres",
   "home": "Chicago Cubs",
   "pick": "Chicago Cubs",
   "model": 0.531,
   "market": 0.526,
   "edge": 0.004,
   "model_side": "Chicago Cubs",
   "model_conf": 0.531,
   "raw_conf": 0.589,
   "raw_model": 0.589,
   "calibrated": true,
   "dec_odds": 1.826,
   "best_dec_odds": 1.87,
   "start": "2026-07-01T18:21:00Z",
   "hp": "Colin Rea",
   "ap": "Walker Buehler",
   "hp_stat": {
    "era": "4.80",
    "w": 5,
    "l": 5,
    "ip": "84.1",
    "so": 63
   },
   "ap_stat": {
    "era": "3.81",
    "w": 5,
    "l": 3,
    "ip": "78.0",
    "so": 70
   },
   "changed": "price +109\u2192-115 \u00b7 pick\u2192Chicago Cubs",
   "frozen": true
  },
  {
   "away": "Miami Marlins",
   "home": "Colorado Rockies",
   "pick": "Miami Marlins",
   "model": 0.535,
   "market": 0.533,
   "edge": 0.002,
   "model_side": "Miami Marlins",
   "model_conf": 0.535,
   "raw_conf": 0.637,
   "raw_model": 0.637,
   "calibrated": true,
   "dec_odds": 1.807,
   "best_dec_odds": 1.82,
   "start": "2026-07-02T19:11:00Z",
   "hp": "Kyle Freeland",
   "ap": "Max Meyer",
   "hp_stat": {
    "era": "7.50",
    "w": 1,
    "l": 7,
    "ip": "72.0",
    "so": 61
   },
   "ap_stat": {
    "era": "2.60",
    "w": 9,
    "l": 0,
    "ip": "97.0",
    "so": 107
   },
   "changed": "edge +4.9\u2192+0.2 \u00b7 price +137\u2192-122 \u00b7 pick\u2192Miami Marlins"
  }
 ]
}